setup.py
normy/__init__.py
normy/database.py
normy.egg-info/PKG-INFO
normy.egg-info/SOURCES.txt
normy.egg-info/dependency_links.txt
normy.egg-info/requires.txt
normy.egg-info/top_level.txt