Metadata-Version: 1.0
Name: normy
Version: 0.11
Summary: Not an ORM Yet
Home-page: https://github.com/shadrus/normy
Author: Yury Krylov
Author-email: UNKNOWN
License: MIT
Platform: UNKNOWN
